ffprobe3/__init__.py
ffprobe3/exceptions.py
ffprobe3/ffprobe.py
ffprobe3_esarjeant-0.1.3.dist-info/LICENSE.txt
ffprobe3_esarjeant-0.1.3.dist-info/METADATA
ffprobe3_esarjeant-0.1.3.dist-info/WHEEL
ffprobe3_esarjeant-0.1.3.dist-info/top_level.txt
ffprobe3_esarjeant-0.1.3.dist-info/RECORD
