Metadata-Version: 2.1
Name: ffprobe3-esarjeant
Version: 0.1.3
Summary: 
